LICENSE
MANIFEST.in
README.md
setup.py
aerosolpy/__init__.py
aerosolpy/kinetics.py
aerosolpy/math.py
aerosolpy/mechanics.py
aerosolpy/time.py
aerosolpy/units.py
aerosolpy.egg-info/PKG-INFO
aerosolpy.egg-info/SOURCES.txt
aerosolpy.egg-info/dependency_links.txt
aerosolpy.egg-info/requires.txt
aerosolpy.egg-info/top_level.txt
aerosolpy/growth/__init__.py
aerosolpy/growth/h2so4.py
aerosolpy/growth/kinetic.py
aerosolpy/growth/vbs.py
aerosolpy/growth/volatility.py
aerosolpy/instr/__init__.py
aerosolpy/instr/cpc.py
aerosolpy/instr/dma.py
aerosolpy/instr/mpss.py