Metadata-Version: 2.1
Name: aerosolpy
Version: 1.0.0
Summary: aerosolpy is a collection of functions and classes useful in calculations related to aerosol science
Home-page: https://github.com/DominikStolzenburg/aerosolpy
Author: Dominik Stolzenburg
Author-email: dominik.stolzenburg@tuwien.ac.at
License: MIT
Classifier: Intended Audience :: Science/Research
Classifier: Programming Language :: Python :: 3.9
License-File: LICENSE
Requires-Dist: numpy>=1.21
Requires-Dist: scipy>=1.7.3
Requires-Dist: pandas>=1.4.2
